marshmallow_jsonschema/__init__.py
marshmallow_jsonschema/base.py
marshmallow_jsonschema/exceptions.py
marshmallow_jsonschema/validation.py
marshmallow_jsonschema/extensions/__init__.py
marshmallow_jsonschema/extensions/react_jsonschema_form.py
marshmallow_jsonschema_python3-0.13.1.dist-info/licenses/LICENSE
marshmallow_jsonschema_python3-0.13.1.dist-info/METADATA
marshmallow_jsonschema_python3-0.13.1.dist-info/WHEEL
marshmallow_jsonschema_python3-0.13.1.dist-info/top_level.txt
marshmallow_jsonschema_python3-0.13.1.dist-info/RECORD
