Metadata-Version: 2.4
Name: marshmallow-jsonschema-python3
Version: 0.13.1
Summary: JSON Schema Draft v7 (http://json-schema.org/) formatting with marshmallow, supports at least Python 3.12, maybe higher.
Home-page: https://github.com/fuhrysteve/marshmallow-jsonschema
Author: Stephen Fuhry
Author-email: fuhrysteve@gmail.com
License: MIT License
Keywords: marshmallow-jsonschema marshmallow schema serialization jsonschema validation
Classifier: Intended Audience :: Developers
Classifier: License :: OSI Approved :: MIT License
Classifier: Natural Language :: English
Classifier: Programming Language :: Python :: 3
Classifier: Programming Language :: Python :: 3.8
Classifier: Programming Language :: Python :: 3.9
Classifier: Programming Language :: Python :: 3.10
Classifier: Programming Language :: Python :: 3.11
Classifier: Programming Language :: Python :: 3.12
Requires-Python: >=3.6
License-File: LICENSE
Requires-Dist: marshmallow>=3.11
Provides-Extra: enum
Requires-Dist: marshmallow-enum; extra == "enum"
Provides-Extra: union
Requires-Dist: marshmallow-union; extra == "union"
Dynamic: author
Dynamic: author-email
Dynamic: classifier
Dynamic: description
Dynamic: description-content-type
Dynamic: home-page
Dynamic: keywords
Dynamic: license
Dynamic: license-file
Dynamic: provides-extra
Dynamic: requires-dist
Dynamic: requires-python
Dynamic: summary
